millionways/__init__.py
millionways/_base_client.py
millionways/_client.py
millionways/_compat.py
millionways/_constants.py
millionways/_exceptions.py
millionways/_files.py
millionways/_models.py
millionways/_qs.py
millionways/_resource.py
millionways/_response.py
millionways/_streaming.py
millionways/_types.py
millionways/_version.py
millionways/py.typed
millionways/_utils/__init__.py
millionways/_utils/_logs.py
millionways/_utils/_proxy.py
millionways/_utils/_reflection.py
millionways/_utils/_resources_proxy.py
millionways/_utils/_streams.py
millionways/_utils/_sync.py
millionways/_utils/_transform.py
millionways/_utils/_typing.py
millionways/_utils/_utils.py
millionways/lib/.keep
millionways/resources/__init__.py
millionways/resources/analyze_team.py
millionways/resources/categorize_audio.py
millionways/resources/categorize_text.py
millionways/resources/chat.py
millionways/resources/chat_result.py
millionways/resources/chat_stream.py
millionways/resources/create_user.py
millionways/resources/get_call.py
millionways/resources/get_user.py
millionways/resources/get_user_analysis.py
millionways/resources/get_user_chats.py
millionways/resources/mental_health_chatbot.py
millionways/resources/sales_assistant.py
millionways/resources/summarize.py
millionways/types/__init__.py
millionways/types/analyze_team_create_params.py
millionways/types/analyze_team_create_response.py
millionways/types/categorize_audio_create_for_user_params.py
millionways/types/categorize_audio_create_for_user_response.py
millionways/types/categorize_audio_create_params.py
millionways/types/categorize_audio_create_response.py
millionways/types/categorize_text_classify_by_user_params.py
millionways/types/categorize_text_classify_by_user_response.py
millionways/types/categorize_text_classify_params.py
millionways/types/categorize_text_classify_response.py
millionways/types/chat_generate_response_for_user_params.py
millionways/types/chat_generate_response_for_user_response.py
millionways-1.0.1.dist-info/METADATA
millionways-1.0.1.dist-info/WHEEL
millionways-1.0.1.dist-info/licenses/LICENSE
millionways-1.0.1.dist-info/RECORD
